KissCartoon.py
kisscartoon_api-0.1.dist-info/DESCRIPTION.rst
kisscartoon_api-0.1.dist-info/METADATA
kisscartoon_api-0.1.dist-info/RECORD
kisscartoon_api-0.1.dist-info/WHEEL
kisscartoon_api-0.1.dist-info/metadata.json
kisscartoon_api-0.1.dist-info/top_level.txt
