Metadata-Version: 2.0
Name: kisscartoon-api
Version: 0.1
Summary: The unofficial API for KissCartoon websites
Home-page: https://github.com/Thyrst/KissCartoon-API
Author: Thyrst
Author-email: thyrst@seznam.cz
License: MIT
Download-URL: https://github.com/Thyrst/KissCartoon-API/archive/0.1.tar.gz
Keywords: API kisscartoon
Platform: UNKNOWN
Classifier: Development Status :: 4 - Beta
Classifier: Intended Audience :: Developers
Classifier: License :: OSI Approved :: MIT License
Classifier: Natural Language :: English
Classifier: Topic :: Software Development :: Libraries :: Python Modules
Classifier: Programming Language :: Python :: 3
Classifier: Topic :: Internet :: WWW/HTTP :: Browsers
Classifier: Topic :: Internet :: WWW/HTTP :: Indexing/Search
Classifier: Topic :: Utilities
Requires-Dist: grab
Requires-Dist: js2py
Requires-Dist: lxml
Requires-Dist: pycurl
